setup.cfg
setup.py
borest/__init__.py
borest/borest.py
bottle_oop_rest.egg-info/PKG-INFO
bottle_oop_rest.egg-info/SOURCES.txt
bottle_oop_rest.egg-info/dependency_links.txt
bottle_oop_rest.egg-info/requires.txt
bottle_oop_rest.egg-info/top_level.txt