Metadata-Version: 1.0
Name: bottle-oop-rest
Version: 0.0.4
Summary: Bottle.py OOP REST simple library
Home-page: https://github.com/jar3b/bottle-oop-rest
Author: hello
Author-email: hellotan@live.ru
License: MIT
Platform: UNKNOWN
